ph_llmops/__init__.py
ph_llmops/prompting/__init__.py
ph_llmops/prompting/builder.py
ph_llmops/prompting/reader.py
ph_llmops/prompting/types.py
ph_llmops/prompting/utils.py
ph_llmops-0.0.2.dist-info/METADATA
ph_llmops-0.0.2.dist-info/WHEEL
ph_llmops-0.0.2.dist-info/top_level.txt
ph_llmops-0.0.2.dist-info/RECORD
